{
    "posters": [
        {
            "id":1,
            "url":"images/posters/1aclass.jpg"
        },
        {
            "id":2,
            "url":"images/posters/bakugo.jpg"
        },
        {
            "id":3,
            "url":"images/posters/deku-shigaraki.jpg"
        },
        {
            "id":4,
            "url":"images/posters/deku1.jpg"
        },
        {
            "id":5,
            "url":"images/posters/deku2.jpg"
        },
        {
            "id":6,
            "url":"images/posters/endevor-hawks.jpg"
        },
        {
            "id":7,
            "url":"images/posters/mha_7th_heroes_main.jpg"
        },
        {
            "id":8,
            "url":"images/posters/mha_7th_villains_fix-main.jpg"
        },
        {
            "id":9,
            "url":"images/posters/oneforall.jpg"
        },
        {
            "id":10,
            "url":"images/posters/starandstripe.jpg"
        },
        {
            "id":11,
            "url":"images/posters/todoroki.jpg"
        },
        {
            "id":12,
            "url":"images/posters/uraraka-toga.jpg"
        },
        {
            "id":13,
            "url":"images/posters/mainposter.jpg"
        }
    ]
}